unique_toolkit/__init__.py
unique_toolkit/_common/_base_service.py
unique_toolkit/_common/_time_utils.py
unique_toolkit/_common/api_calling/human_verification_manager.py
unique_toolkit/_common/base_model_type_attribute.py
unique_toolkit/_common/chunk_relevancy_sorter/config.py
unique_toolkit/_common/chunk_relevancy_sorter/exception.py
unique_toolkit/_common/chunk_relevancy_sorter/schemas.py
unique_toolkit/_common/chunk_relevancy_sorter/service.py
unique_toolkit/_common/chunk_relevancy_sorter/tests/test_service.py
unique_toolkit/_common/default_language_model.py
unique_toolkit/_common/docx_generator/__init__.py
unique_toolkit/_common/docx_generator/config.py
unique_toolkit/_common/docx_generator/schemas.py
unique_toolkit/_common/docx_generator/service.py
unique_toolkit/_common/docx_generator/template/Doc Template.docx
unique_toolkit/_common/endpoint_builder.py
unique_toolkit/_common/endpoint_requestor.py
unique_toolkit/_common/exception.py
unique_toolkit/_common/execution.py
unique_toolkit/_common/experimental/endpoint_builder.py
unique_toolkit/_common/experimental/endpoint_requestor.py
unique_toolkit/_common/experimental/write_up_agent/README.md
unique_toolkit/_common/experimental/write_up_agent/__init__.py
unique_toolkit/_common/experimental/write_up_agent/agent.py
unique_toolkit/_common/experimental/write_up_agent/config.py
unique_toolkit/_common/experimental/write_up_agent/examples/data.csv
unique_toolkit/_common/experimental/write_up_agent/examples/example_usage.py
unique_toolkit/_common/experimental/write_up_agent/schemas.py
unique_toolkit/_common/experimental/write_up_agent/services/__init__.py
unique_toolkit/_common/experimental/write_up_agent/services/dataframe_handler/__init__.py
unique_toolkit/_common/experimental/write_up_agent/services/dataframe_handler/exceptions.py
unique_toolkit/_common/experimental/write_up_agent/services/dataframe_handler/service.py
unique_toolkit/_common/experimental/write_up_agent/services/dataframe_handler/utils.py
unique_toolkit-1.45.7.dist-info/LICENSE
unique_toolkit-1.45.7.dist-info/METADATA
unique_toolkit-1.45.7.dist-info/WHEEL
unique_toolkit-1.45.7.dist-info/RECORD
