Metadata-Version: 2.1
Name: unique_toolkit
Version: 1.45.7
Summary: 
License: Proprietary
Author: Cedric Klinkert
Author-email: cedric.klinkert@unique.ch
Requires-Python: >=3.12,<4.0
Classifier: License :: Other/Proprietary License
Classifier: Programming Language :: Python :: 3
Classifier: Programming Language :: Python :: 3.12
Requires-Dist: aiohttp (>=3.12.0,<4.0.0)
Requires-Dist: docxtpl (>=0.20.1,<0.21.0)
Requires-Dist: httpx (>=0.28.0,<0.29.0)
Requires-Dist: jambo (>=0.1.2,<0.2.0)
Requires-Dist: jinja2 (>=3.1.6,<4.0.0)
Requires-Dist: markdown-it-py (>=4.0.0,<5.0.0)
Requires-Dist: numpy (>=2.1.0,<3.0.0)
Requires-Dist: openai (>=1.99.9,<2.0.0)
Requires-Dist: pandas (>=2.3.0,<3.0.0)
Requires-Dist: pillow (>=10.4.0,<11.0.0)
Requires-Dist: platformdirs (>=4.0.0,<5.0.0)
Requires-Dist: pydantic (>=2.8.2,<3.0.0)
Requires-Dist: pydantic-settings (>=2.10.1,<3.0.0)
Requires-Dist: pyhumps (>=3.8.0,<4.0.0)
Requires-Dist: python-docx (>=1.1.0,<2.0.0)
Requires-Dist: regex (>=2024.5.15,<2025.0.0)
Requires-Dist: requests (>=2.32.0,<3.0.0)
Requires-Dist: sseclient (>=0.0.27,<0.0.28)
Requires-Dist: tiktoken (>=0.12.0,<0.13.0)
Requires-Dist: typing-extensions (>=4.9.0,<5.0.0)
Requires-Dist: unique-sdk (>=0.10.67,<0.11.0)
